js2x/__main__.py
js2x-0.0.8.dist-info/DESCRIPTION.rst
js2x-0.0.8.dist-info/METADATA
js2x-0.0.8.dist-info/RECORD
js2x-0.0.8.dist-info/WHEEL
js2x-0.0.8.dist-info/metadata.json
js2x-0.0.8.dist-info/top_level.txt
