Metadata-Version: 2.0
Name: js2x
Version: 0.0.8
Summary: Download JianShu article as markdown file.
Home-page: https://github.com/boboidream/js2x
Author: boboidream
Author-email: z644381492@gmail.com
License: MIT
Keywords: jianshu hexo markdown
Platform: UNKNOWN
Classifier: Development Status :: 4 - Beta
Classifier: Intended Audience :: Developers
Classifier: Topic :: Software Development :: Build Tools
Classifier: License :: OSI Approved :: MIT License
Classifier: Programming Language :: Python :: 2.6
Classifier: Programming Language :: Python :: 2.7
Classifier: Programming Language :: Python :: 3
Classifier: Programming Language :: Python :: 3.3
Classifier: Programming Language :: Python :: 3.4
Classifier: Programming Language :: Python :: 3.5
